odoo/addons/ssi_multiple_approval_mixin/README.rst
odoo/addons/ssi_multiple_approval_mixin/__init__.py
odoo/addons/ssi_multiple_approval_mixin/__manifest__.py
odoo/addons/ssi_multiple_approval_mixin/menu.xml
odoo/addons/ssi_multiple_approval_mixin/i18n/ssi_multiple_approval_mixin.pot
odoo/addons/ssi_multiple_approval_mixin/models/__init__.py
odoo/addons/ssi_multiple_approval_mixin/models/approval_approval.py
odoo/addons/ssi_multiple_approval_mixin/models/approval_template.py
odoo/addons/ssi_multiple_approval_mixin/models/approval_template_detail.py
odoo/addons/ssi_multiple_approval_mixin/models/mixin_multiple_approval.py
odoo/addons/ssi_multiple_approval_mixin/security/ir.model.access.csv
odoo/addons/ssi_multiple_approval_mixin/static/description/icon.png
odoo/addons/ssi_multiple_approval_mixin/templates/mixin_multiple_approval_templates.xml
odoo/addons/ssi_multiple_approval_mixin/views/approval_approval_views.xml
odoo/addons/ssi_multiple_approval_mixin/views/approval_template_detail_views.xml
odoo/addons/ssi_multiple_approval_mixin/views/approval_template_views.xml
odoo14_addon_ssi_multiple_approval_mixin-14.0.1.10.2.dist-info/METADATA
odoo14_addon_ssi_multiple_approval_mixin-14.0.1.10.2.dist-info/WHEEL
odoo14_addon_ssi_multiple_approval_mixin-14.0.1.10.2.dist-info/top_level.txt
odoo14_addon_ssi_multiple_approval_mixin-14.0.1.10.2.dist-info/RECORD
